<profile>

<ReportVersion>
<Version>2019.1</Version>
</ReportVersion>

<UserAssignments>
<unit>ns</unit>
<ProductFamily>kintex7</ProductFamily>
<Part>xc7k325t-ffg900-2</Part>
<TopModelName>AXIvideo2Mat2</TopModelName>
<TargetClockPeriod>10.00</TargetClockPeriod>
<ClockUncertainty>1.25</ClockUncertainty>
</UserAssignments>

<PerformanceEstimates>
<PipelineType>none</PipelineType>
<SummaryOfTimingAnalysis>
<unit>ns</unit>
<EstimatedClockPeriod>2.468</EstimatedClockPeriod>
</SummaryOfTimingAnalysis>
<SummaryOfOverallLatency>
<unit>clock cycles</unit>
<Best-caseLatency>645</Best-caseLatency>
<Average-caseLatency>646</Average-caseLatency>
<Worst-caseLatency>646</Worst-caseLatency>
<Interval-min>645</Interval-min>
<Interval-max>646</Interval-max>
</SummaryOfOverallLatency>
<SummaryOfLoopLatency>
<loop_wait_for_start>
<TripCount>0</TripCount>
<Latency>0</Latency>
<PipelineII>1</PipelineII>
<PipelineDepth>1</PipelineDepth>
</loop_wait_for_start>
<loop_width>
<TripCount>640</TripCount>
<Latency>640</Latency>
<PipelineII>1</PipelineII>
<PipelineDepth>2</PipelineDepth>
</loop_width>
<loop_wait_for_eol>
<TripCount>0</TripCount>
<Latency>0</Latency>
<PipelineII>1</PipelineII>
<PipelineDepth>1</PipelineDepth>
</loop_wait_for_eol>
</SummaryOfLoopLatency>
</PerformanceEstimates>

<AreaEstimates>
<Resources>
<FF>166</FF>
<LUT>364</LUT>
<BRAM_18K>0</BRAM_18K>
<DSP48E>0</DSP48E>
<URAM>0</URAM>
</Resources>
<AvailableResources>
<BRAM_18K>890</BRAM_18K>
<DSP48E>840</DSP48E>
<FF>407600</FF>
<LUT>203800</LUT>
<URAM>0</URAM>
</AvailableResources>
</AreaEstimates>

<InterfaceSummary>
<RtlPorts>
<name>ap_clk</name>
<Object>AXIvideo2Mat2</Object>
<Type>return value</Type>
<Scope></Scope>
<IOProtocol>ap_ctrl_hs</IOProtocol>
<IOConfig></IOConfig>
<Dir>in</Dir>
<Bits>1</Bits>
<Attribute>control</Attribute>
</RtlPorts>
<RtlPorts>
<name>ap_rst</name>
<Object>AXIvideo2Mat2</Object>
<Type>return value</Type>
<Scope></Scope>
<IOProtocol>ap_ctrl_hs</IOProtocol>
<IOConfig></IOConfig>
<Dir>in</Dir>
<Bits>1</Bits>
<Attribute>control</Attribute>
</RtlPorts>
<RtlPorts>
<name>ap_start</name>
<Object>AXIvideo2Mat2</Object>
<Type>return value</Type>
<Scope></Scope>
<IOProtocol>ap_ctrl_hs</IOProtocol>
<IOConfig></IOConfig>
<Dir>in</Dir>
<Bits>1</Bits>
<Attribute>control</Attribute>
</RtlPorts>
<RtlPorts>
<name>ap_done</name>
<Object>AXIvideo2Mat2</Object>
<Type>return value</Type>
<Scope></Scope>
<IOProtocol>ap_ctrl_hs</IOProtocol>
<IOConfig></IOConfig>
<Dir>out</Dir>
<Bits>1</Bits>
<Attribute>control</Attribute>
</RtlPorts>
<RtlPorts>
<name>ap_idle</name>
<Object>AXIvideo2Mat2</Object>
<Type>return value</Type>
<Scope></Scope>
<IOProtocol>ap_ctrl_hs</IOProtocol>
<IOConfig></IOConfig>
<Dir>out</Dir>
<Bits>1</Bits>
<Attribute>control</Attribute>
</RtlPorts>
<RtlPorts>
<name>ap_ready</name>
<Object>AXIvideo2Mat2</Object>
<Type>return value</Type>
<Scope></Scope>
<IOProtocol>ap_ctrl_hs</IOProtocol>
<IOConfig></IOConfig>
<Dir>out</Dir>
<Bits>1</Bits>
<Attribute>control</Attribute>
</RtlPorts>
<RtlPorts>
<name>ap_return</name>
<Object>AXIvideo2Mat2</Object>
<Type>return value</Type>
<Scope></Scope>
<IOProtocol>ap_ctrl_hs</IOProtocol>
<IOConfig></IOConfig>
<Dir>out</Dir>
<Bits>1</Bits>
<Attribute>data</Attribute>
</RtlPorts>
<RtlPorts>
<name>src_axi0_TDATA</name>
<Object>AXI_video_strm_V_data_V</Object>
<Type>pointer</Type>
<Scope></Scope>
<IOProtocol>axis</IOProtocol>
<IOConfig>register, both mode</IOConfig>
<Dir>in</Dir>
<Bits>24</Bits>
<Attribute>data</Attribute>
</RtlPorts>
<RtlPorts>
<name>src_axi0_TVALID</name>
<Object>AXI_video_strm_V_dest_V</Object>
<Type>pointer</Type>
<Scope></Scope>
<IOProtocol>axis</IOProtocol>
<IOConfig>register, both mode</IOConfig>
<Dir>in</Dir>
<Bits>1</Bits>
<Attribute>control</Attribute>
</RtlPorts>
<RtlPorts>
<name>src_axi0_TREADY</name>
<Object>AXI_video_strm_V_dest_V</Object>
<Type>pointer</Type>
<Scope></Scope>
<IOProtocol>axis</IOProtocol>
<IOConfig>register, both mode</IOConfig>
<Dir>out</Dir>
<Bits>1</Bits>
<Attribute>control</Attribute>
</RtlPorts>
<RtlPorts>
<name>src_axi0_TDEST</name>
<Object>AXI_video_strm_V_dest_V</Object>
<Type>pointer</Type>
<Scope></Scope>
<IOProtocol>axis</IOProtocol>
<IOConfig>register, both mode</IOConfig>
<Dir>in</Dir>
<Bits>1</Bits>
<Attribute>data</Attribute>
</RtlPorts>
<RtlPorts>
<name>src_axi0_TKEEP</name>
<Object>AXI_video_strm_V_keep_V</Object>
<Type>pointer</Type>
<Scope></Scope>
<IOProtocol>axis</IOProtocol>
<IOConfig>register, both mode</IOConfig>
<Dir>in</Dir>
<Bits>3</Bits>
<Attribute>data</Attribute>
</RtlPorts>
<RtlPorts>
<name>src_axi0_TSTRB</name>
<Object>AXI_video_strm_V_strb_V</Object>
<Type>pointer</Type>
<Scope></Scope>
<IOProtocol>axis</IOProtocol>
<IOConfig>register, both mode</IOConfig>
<Dir>in</Dir>
<Bits>3</Bits>
<Attribute>data</Attribute>
</RtlPorts>
<RtlPorts>
<name>src_axi0_TUSER</name>
<Object>AXI_video_strm_V_user_V</Object>
<Type>pointer</Type>
<Scope></Scope>
<IOProtocol>axis</IOProtocol>
<IOConfig>register, both mode</IOConfig>
<Dir>in</Dir>
<Bits>1</Bits>
<Attribute>data</Attribute>
</RtlPorts>
<RtlPorts>
<name>src_axi0_TLAST</name>
<Object>AXI_video_strm_V_last_V</Object>
<Type>pointer</Type>
<Scope></Scope>
<IOProtocol>axis</IOProtocol>
<IOConfig>register, both mode</IOConfig>
<Dir>in</Dir>
<Bits>1</Bits>
<Attribute>data</Attribute>
</RtlPorts>
<RtlPorts>
<name>src_axi0_TID</name>
<Object>AXI_video_strm_V_id_V</Object>
<Type>pointer</Type>
<Scope></Scope>
<IOProtocol>axis</IOProtocol>
<IOConfig>register, both mode</IOConfig>
<Dir>in</Dir>
<Bits>1</Bits>
<Attribute>data</Attribute>
</RtlPorts>
<RtlPorts>
<name>img_data_stream_0_V_din</name>
<Object>img_data_stream_0_V</Object>
<Type>pointer</Type>
<Scope></Scope>
<IOProtocol>ap_fifo</IOProtocol>
<IOConfig></IOConfig>
<Dir>out</Dir>
<Bits>8</Bits>
<Attribute>control</Attribute>
</RtlPorts>
<RtlPorts>
<name>img_data_stream_0_V_full_n</name>
<Object>img_data_stream_0_V</Object>
<Type>pointer</Type>
<Scope></Scope>
<IOProtocol>ap_fifo</IOProtocol>
<IOConfig></IOConfig>
<Dir>in</Dir>
<Bits>1</Bits>
<Attribute>control</Attribute>
</RtlPorts>
<RtlPorts>
<name>img_data_stream_0_V_write</name>
<Object>img_data_stream_0_V</Object>
<Type>pointer</Type>
<Scope></Scope>
<IOProtocol>ap_fifo</IOProtocol>
<IOConfig></IOConfig>
<Dir>out</Dir>
<Bits>1</Bits>
<Attribute>control</Attribute>
</RtlPorts>
<RtlPorts>
<name>img_data_stream_1_V_din</name>
<Object>img_data_stream_1_V</Object>
<Type>pointer</Type>
<Scope></Scope>
<IOProtocol>ap_fifo</IOProtocol>
<IOConfig></IOConfig>
<Dir>out</Dir>
<Bits>8</Bits>
<Attribute>control</Attribute>
</RtlPorts>
<RtlPorts>
<name>img_data_stream_1_V_full_n</name>
<Object>img_data_stream_1_V</Object>
<Type>pointer</Type>
<Scope></Scope>
<IOProtocol>ap_fifo</IOProtocol>
<IOConfig></IOConfig>
<Dir>in</Dir>
<Bits>1</Bits>
<Attribute>control</Attribute>
</RtlPorts>
<RtlPorts>
<name>img_data_stream_1_V_write</name>
<Object>img_data_stream_1_V</Object>
<Type>pointer</Type>
<Scope></Scope>
<IOProtocol>ap_fifo</IOProtocol>
<IOConfig></IOConfig>
<Dir>out</Dir>
<Bits>1</Bits>
<Attribute>control</Attribute>
</RtlPorts>
<RtlPorts>
<name>img_data_stream_2_V_din</name>
<Object>img_data_stream_2_V</Object>
<Type>pointer</Type>
<Scope></Scope>
<IOProtocol>ap_fifo</IOProtocol>
<IOConfig></IOConfig>
<Dir>out</Dir>
<Bits>8</Bits>
<Attribute>control</Attribute>
</RtlPorts>
<RtlPorts>
<name>img_data_stream_2_V_full_n</name>
<Object>img_data_stream_2_V</Object>
<Type>pointer</Type>
<Scope></Scope>
<IOProtocol>ap_fifo</IOProtocol>
<IOConfig></IOConfig>
<Dir>in</Dir>
<Bits>1</Bits>
<Attribute>control</Attribute>
</RtlPorts>
<RtlPorts>
<name>img_data_stream_2_V_write</name>
<Object>img_data_stream_2_V</Object>
<Type>pointer</Type>
<Scope></Scope>
<IOProtocol>ap_fifo</IOProtocol>
<IOConfig></IOConfig>
<Dir>out</Dir>
<Bits>1</Bits>
<Attribute>control</Attribute>
</RtlPorts>
<RtlPorts>
<name>p_row</name>
<Object>p_row</Object>
<Type>scalar</Type>
<Scope></Scope>
<IOProtocol>ap_none</IOProtocol>
<IOConfig></IOConfig>
<Dir>in</Dir>
<Bits>11</Bits>
<Attribute>data</Attribute>
</RtlPorts>
<RtlPorts>
<name>sof_read</name>
<Object>sof_read</Object>
<Type>scalar</Type>
<Scope></Scope>
<IOProtocol>ap_none</IOProtocol>
<IOConfig></IOConfig>
<Dir>in</Dir>
<Bits>1</Bits>
<Attribute>data</Attribute>
</RtlPorts>
</InterfaceSummary>

</profile>
